LICENSE.md
MANIFEST.in
README.rst
pyproject.toml
requirements.core.txt
requirements.txt
setup.py
core_user_registration_app/__init__.py
core_user_registration_app/admin.py
core_user_registration_app/apps.py
core_user_registration_app/discover.py
core_user_registration_app/menus.py
core_user_registration_app/models.py
core_user_registration_app/settings.py
core_user_registration_app/tasks.py
core_user_registration_app/urls.py
core_user_registration_app.egg-info/PKG-INFO
core_user_registration_app.egg-info/SOURCES.txt
core_user_registration_app.egg-info/dependency_links.txt
core_user_registration_app.egg-info/requires.txt
core_user_registration_app.egg-info/top_level.txt
core_user_registration_app/access_control/__init__.py
core_user_registration_app/access_control/api.py
core_user_registration_app/components/__init__.py
core_user_registration_app/components/account_request_metadata/__init__.py
core_user_registration_app/components/account_request_metadata/api.py
core_user_registration_app/components/account_request_metadata/models.py
core_user_registration_app/components/user_data_structure/__init__.py
core_user_registration_app/components/user_data_structure/api.py
core_user_registration_app/components/user_data_structure/models.py
core_user_registration_app/components/user_metadata/__init__.py
core_user_registration_app/components/user_metadata/api.py
core_user_registration_app/components/user_metadata/models.py
core_user_registration_app/components/user_template_version_manager/__init__.py
core_user_registration_app/components/user_template_version_manager/access_control.py
core_user_registration_app/components/user_template_version_manager/api.py
core_user_registration_app/components/user_template_version_manager/models.py
core_user_registration_app/migrations/0001_initial.py
core_user_registration_app/migrations/0002_template_formats.py
core_user_registration_app/migrations/0003_init_data.py
core_user_registration_app/migrations/0004_file_history.py
core_user_registration_app/migrations/__init__.py
core_user_registration_app/permissions/__init__.py
core_user_registration_app/permissions/rights.py
core_user_registration_app/static/core_user_registration_app/admin/js/view_meta.js
