Metadata-Version: 2.1
Name: core-user-registration-app
Version: 2.19.0
Summary: User registration module for the core project
Home-page: https://github.com/usnistgov/core_user_registration_app
Author: NIST IT Lab
Author-email: itl_inquiries@nist.gov
License-File: LICENSE.md
